{"inputs":{"node_modules/react/cjs/react.development.js":{"bytes":87574,"imports":[],"format":"cjs"},"node_modules/react/index.js":{"bytes":190,"imports":[{"path":"node_modules/react/cjs/react.development.js","kind":"require-call","original":"./cjs/react.development.js"}],"format":"cjs"},"node_modules/scheduler/cjs/scheduler.development.js":{"bytes":17497,"imports":[],"format":"cjs"},"node_modules/scheduler/index.js":{"bytes":198,"imports":[{"path":"node_modules/scheduler/cjs/scheduler.development.js","kind":"require-call","original":"./cjs/scheduler.development.js"}],"format":"cjs"},"node_modules/react-dom/cjs/react-dom.development.js":{"bytes":1026501,"imports":[{"path":"node_modules/react/index.js","kind":"require-call","original":"react"},{"path":"node_modules/scheduler/index.js","kind":"require-call","original":"scheduler"}],"format":"cjs"},"node_modules/react-dom/index.js":{"bytes":1363,"imports":[{"path":"node_modules/react-dom/cjs/react-dom.development.js","kind":"require-call","original":"./cjs/react-dom.development.js"}],"format":"cjs"},"node_modules/@remix-run/router/dist/router.js":{"bytes":197294,"imports":[],"format":"esm"},"node_modules/react-router/dist/index.js":{"bytes":60855,"imports":[{"path":"node_modules/react/index.js","kind":"import-statement","original":"react"},{"path":"node_modules/@remix-run/router/dist/router.js","kind":"import-statement","original":"@remix-run/router"},{"path":"node_modules/@remix-run/router/dist/router.js","kind":"import-statement","original":"@remix-run/router"}],"format":"esm"},"node_modules/react-router-dom/dist/index.js":{"bytes":56722,"imports":[{"path":"node_modules/react/index.js","kind":"import-statement","original":"react"},{"path":"node_modules/react-dom/index.js","kind":"import-statement","original":"react-dom"},{"path":"node_modules/react-router/dist/index.js","kind":"import-statement","original":"react-router"},{"path":"node_modules/react-router/dist/index.js","kind":"import-statement","original":"react-router"},{"path":"node_modules/@remix-run/router/dist/router.js","kind":"import-statement","original":"@remix-run/router"},{"path":"node_modules/@remix-run/router/dist/router.js","kind":"import-statement","original":"@remix-run/router"}],"format":"esm"},"node_modules/cookie/index.js":{"bytes":5281,"imports":[],"format":"cjs"},"node_modules/@remix-run/server-runtime/dist/esm/warnings.js":{"bytes":439,"imports":[],"format":"esm"},"node_modules/@remix-run/server-runtime/dist/esm/cookies.js":{"bytes":4989,"imports":[{"path":"node_modules/cookie/index.js","kind":"import-statement","original":"cookie"},{"path":"node_modules/@remix-run/server-runtime/dist/esm/warnings.js","kind":"import-statement","original":"./warnings.js"}],"format":"esm"},"node_modules/@web3-storage/multipart-parser/esm/src/utils.js":{"bytes":722,"imports":[],"format":"esm"},"node_modules/@web3-storage/multipart-parser/esm/src/search.js":{"bytes":6918,"imports":[{"path":"node_modules/@web3-storage/multipart-parser/esm/src/utils.js","kind":"import-statement","original":"./utils.js"}],"format":"esm"},"node_modules/@web3-storage/multipart-parser/esm/src/index.js":{"bytes":6352,"imports":[{"path":"node_modules/@web3-storage/multipart-parser/esm/src/search.js","kind":"import-statement","original":"./search.js"},{"path":"node_modules/@web3-storage/multipart-parser/esm/src/utils.js","kind":"import-statement","original":"./utils.js"}],"format":"esm"},"node_modules/@remix-run/server-runtime/dist/esm/formData.js":{"bytes":1713,"imports":[{"path":"node_modules/@web3-storage/multipart-parser/esm/src/index.js","kind":"import-statement","original":"@web3-storage/multipart-parser"}],"format":"esm"},"node_modules/@remix-run/server-runtime/dist/esm/mode.js":{"bytes":667,"imports":[],"format":"esm"},"node_modules/@remix-run/server-runtime/dist/esm/errors.js":{"bytes":4411,"imports":[{"path":"node_modules/@remix-run/router/dist/router.js","kind":"import-statement","original":"@remix-run/router"},{"path":"node_modules/@remix-run/server-runtime/dist/esm/mode.js","kind":"import-statement","original":"./mode.js"}],"format":"esm"},"node_modules/@remix-run/server-runtime/dist/esm/responses.js":{"bytes":5167,"imports":[{"path":"node_modules/@remix-run/router/dist/router.js","kind":"import-statement","original":"@remix-run/router"},{"path":"node_modules/@remix-run/server-runtime/dist/esm/errors.js","kind":"import-statement","original":"./errors.js"}],"format":"esm"},"node_modules/turbo-stream/dist/turbo-stream.mjs":{"bytes":20283,"imports":[],"format":"esm"},"node_modules/set-cookie-parser/lib/set-cookie.js":{"bytes":6630,"imports":[],"format":"cjs"},"node_modules/@remix-run/server-runtime/dist/esm/headers.js":{"bytes":3674,"imports":[{"path":"node_modules/set-cookie-parser/lib/set-cookie.js","kind":"import-statement","original":"set-cookie-parser"}],"format":"esm"},"node_modules/@remix-run/server-runtime/dist/esm/single-fetch.js":{"bytes":10392,"imports":[{"path":"node_modules/@remix-run/router/dist/router.js","kind":"import-statement","original":"@remix-run/router"},{"path":"node_modules/turbo-stream/dist/turbo-stream.mjs","kind":"import-statement","original":"turbo-stream"},{"path":"node_modules/@remix-run/server-runtime/dist/esm/errors.js","kind":"import-statement","original":"./errors.js"},{"path":"node_modules/@remix-run/server-runtime/dist/esm/headers.js","kind":"import-statement","original":"./headers.js"},{"path":"node_modules/@remix-run/server-runtime/dist/esm/mode.js","kind":"import-statement","original":"./mode.js"},{"path":"node_modules/@remix-run/server-runtime/dist/esm/responses.js","kind":"import-statement","original":"./responses.js"}],"format":"esm"},"node_modules/@remix-run/server-runtime/dist/esm/entry.js":{"bytes":452,"imports":[],"format":"esm"},"node_modules/@remix-run/server-runtime/dist/esm/invariant.js":{"bytes":547,"imports":[],"format":"esm"},"node_modules/@remix-run/server-runtime/dist/esm/routeMatching.js":{"bytes":581,"imports":[{"path":"node_modules/@remix-run/router/dist/router.js","kind":"import-statement","original":"@remix-run/router"}],"format":"esm"},"node_modules/@remix-run/server-runtime/dist/esm/data.js":{"bytes":3806,"imports":[{"path":"node_modules/@remix-run/server-runtime/dist/esm/responses.js","kind":"import-statement","original":"./responses.js"}],"format":"esm"},"node_modules/@remix-run/server-runtime/dist/esm/routes.js":{"bytes":2679,"imports":[{"path":"node_modules/@remix-run/server-runtime/dist/esm/data.js","kind":"import-statement","original":"./data.js"}],"format":"esm"},"node_modules/@remix-run/server-runtime/dist/esm/markup.js":{"bytes":896,"imports":[],"format":"esm"},"node_modules/@remix-run/server-runtime/dist/esm/serverHandoff.js":{"bytes":628,"imports":[{"path":"node_modules/@remix-run/server-runtime/dist/esm/markup.js","kind":"import-statement","original":"./markup.js"}],"format":"esm"},"node_modules/@remix-run/server-runtime/dist/esm/dev.js":{"bytes":1358,"imports":[],"format":"esm"},"node_modules/@remix-run/server-runtime/dist/esm/deprecations.js":{"bytes":825,"imports":[],"format":"esm"},"node_modules/@remix-run/server-runtime/dist/esm/server.js":{"bytes":20652,"imports":[{"path":"node_modules/@remix-run/router/dist/router.js","kind":"import-statement","original":"@remix-run/router"},{"path":"node_modules/@remix-run/server-runtime/dist/esm/entry.js","kind":"import-statement","original":"./entry.js"},{"path":"node_modules/@remix-run/server-runtime/dist/esm/errors.js","kind":"import-statement","original":"./errors.js"},{"path":"node_modules/@remix-run/server-runtime/dist/esm/headers.js","kind":"import-statement","original":"./headers.js"},{"path":"node_modules/@remix-run/server-runtime/dist/esm/invariant.js","kind":"import-statement","original":"./invariant.js"},{"path":"node_modules/@remix-run/server-runtime/dist/esm/mode.js","kind":"import-statement","original":"./mode.js"},{"path":"node_modules/@remix-run/server-runtime/dist/esm/routeMatching.js","kind":"import-statement","original":"./routeMatching.js"},{"path":"node_modules/@remix-run/server-runtime/dist/esm/routes.js","kind":"import-statement","original":"./routes.js"},{"path":"node_modules/@remix-run/server-runtime/dist/esm/responses.js","kind":"import-statement","original":"./responses.js"},{"path":"node_modules/@remix-run/server-runtime/dist/esm/serverHandoff.js","kind":"import-statement","original":"./serverHandoff.js"},{"path":"node_modules/@remix-run/server-runtime/dist/esm/dev.js","kind":"import-statement","original":"./dev.js"},{"path":"node_modules/@remix-run/server-runtime/dist/esm/single-fetch.js","kind":"import-statement","original":"./single-fetch.js"},{"path":"node_modules/@remix-run/server-runtime/dist/esm/deprecations.js","kind":"import-statement","original":"./deprecations.js"}],"format":"esm"},"node_modules/@remix-run/server-runtime/dist/esm/sessions.js":{"bytes":4710,"imports":[{"path":"node_modules/@remix-run/server-runtime/dist/esm/cookies.js","kind":"import-statement","original":"./cookies.js"},{"path":"node_modules/@remix-run/server-runtime/dist/esm/warnings.js","kind":"import-statement","original":"./warnings.js"}],"format":"esm"},"node_modules/@remix-run/server-runtime/dist/esm/sessions/cookieStorage.js":{"bytes":1838,"imports":[{"path":"node_modules/@remix-run/server-runtime/dist/esm/cookies.js","kind":"import-statement","original":"../cookies.js"},{"path":"node_modules/@remix-run/server-runtime/dist/esm/sessions.js","kind":"import-statement","original":"../sessions.js"}],"format":"esm"},"node_modules/@remix-run/server-runtime/dist/esm/sessions/memoryStorage.js":{"bytes":1441,"imports":[],"format":"esm"},"node_modules/@remix-run/server-runtime/dist/esm/upload/errors.js":{"bytes":488,"imports":[],"format":"esm"},"node_modules/@remix-run/server-runtime/dist/esm/upload/memoryUploadHandler.js":{"bytes":1061,"imports":[{"path":"node_modules/@remix-run/server-runtime/dist/esm/upload/errors.js","kind":"import-statement","original":"./errors.js"}],"format":"esm"},"node_modules/@remix-run/server-runtime/dist/esm/index.js":{"bytes":1221,"imports":[{"path":"node_modules/@remix-run/server-runtime/dist/esm/cookies.js","kind":"import-statement","original":"./cookies.js"},{"path":"node_modules/@remix-run/server-runtime/dist/esm/formData.js","kind":"import-statement","original":"./formData.js"},{"path":"node_modules/@remix-run/server-runtime/dist/esm/responses.js","kind":"import-statement","original":"./responses.js"},{"path":"node_modules/@remix-run/server-runtime/dist/esm/single-fetch.js","kind":"import-statement","original":"./single-fetch.js"},{"path":"node_modules/@remix-run/server-runtime/dist/esm/server.js","kind":"import-statement","original":"./server.js"},{"path":"node_modules/@remix-run/server-runtime/dist/esm/sessions.js","kind":"import-statement","original":"./sessions.js"},{"path":"node_modules/@remix-run/server-runtime/dist/esm/sessions/cookieStorage.js","kind":"import-statement","original":"./sessions/cookieStorage.js"},{"path":"node_modules/@remix-run/server-runtime/dist/esm/sessions/memoryStorage.js","kind":"import-statement","original":"./sessions/memoryStorage.js"},{"path":"node_modules/@remix-run/server-runtime/dist/esm/upload/memoryUploadHandler.js","kind":"import-statement","original":"./upload/memoryUploadHandler.js"},{"path":"node_modules/@remix-run/server-runtime/dist/esm/upload/errors.js","kind":"import-statement","original":"./upload/errors.js"},{"path":"node_modules/@remix-run/server-runtime/dist/esm/dev.js","kind":"import-statement","original":"./dev.js"}],"format":"esm"},"node_modules/react-refresh/cjs/react-refresh-runtime.development.js":{"bytes":20419,"imports":[],"format":"cjs"},"node_modules/react-refresh/runtime.js":{"bytes":222,"imports":[{"path":"node_modules/react-refresh/cjs/react-refresh-runtime.development.js","kind":"require-call","original":"./cjs/react-refresh-runtime.development.js"}],"format":"cjs"},"hmr-runtime:remix:hmr":{"bytes":1958,"imports":[{"path":"node_modules/react-refresh/runtime.js","kind":"import-statement","original":"/Users/siyahkare/code/yayinci-lara-remix-fixed/node_modules/react-refresh/runtime.js"}],"format":"esm"},"node_modules/@remix-run/react/dist/esm/_virtual/_rollupPluginBabelHelpers.js":{"bytes":662,"imports":[],"format":"esm"},"node_modules/@remix-run/react/dist/esm/invariant.js":{"bytes":409,"imports":[],"format":"esm"},"node_modules/@remix-run/react/dist/esm/routeModules.js":{"bytes":2905,"imports":[],"format":"esm"},"node_modules/@remix-run/react/dist/esm/links.js":{"bytes":9955,"imports":[{"path":"node_modules/react-router-dom/dist/index.js","kind":"import-statement","original":"react-router-dom"},{"path":"node_modules/@remix-run/react/dist/esm/routeModules.js","kind":"import-statement","original":"./routeModules.js"}],"format":"esm"},"node_modules/@remix-run/react/dist/esm/markup.js":{"bytes":962,"imports":[],"format":"esm"},"node_modules/@remix-run/react/dist/esm/data.js":{"bytes":10265,"imports":[{"path":"node_modules/@remix-run/router/dist/router.js","kind":"import-statement","original":"@remix-run/router"}],"format":"esm"},"node_modules/@remix-run/react/dist/esm/single-fetch.js":{"bytes":14740,"imports":[{"path":"node_modules/react/index.js","kind":"import-statement","original":"react"},{"path":"node_modules/@remix-run/router/dist/router.js","kind":"import-statement","original":"@remix-run/router"},{"path":"node_modules/@remix-run/server-runtime/dist/esm/index.js","kind":"import-statement","original":"@remix-run/server-runtime"},{"path":"node_modules/turbo-stream/dist/turbo-stream.mjs","kind":"import-statement","original":"turbo-stream"},{"path":"node_modules/@remix-run/react/dist/esm/data.js","kind":"import-statement","original":"./data.js"},{"path":"node_modules/@remix-run/react/dist/esm/markup.js","kind":"import-statement","original":"./markup.js"},{"path":"node_modules/@remix-run/react/dist/esm/invariant.js","kind":"import-statement","original":"./invariant.js"}],"format":"esm"},"node_modules/@remix-run/react/dist/esm/errorBoundaries.js":{"bytes":5612,"imports":[{"path":"node_modules/react/index.js","kind":"import-statement","original":"react"},{"path":"node_modules/react-router-dom/dist/index.js","kind":"import-statement","original":"react-router-dom"},{"path":"node_modules/@remix-run/react/dist/esm/components.js","kind":"import-statement","original":"./components.js"}],"format":"esm"},"node_modules/@remix-run/react/dist/esm/fallback.js":{"bytes":1236,"imports":[{"path":"node_modules/react/index.js","kind":"import-statement","original":"react"},{"path":"node_modules/@remix-run/react/dist/esm/errorBoundaries.js","kind":"import-statement","original":"./errorBoundaries.js"}],"format":"esm"},"node_modules/@remix-run/react/dist/esm/routes.js":{"bytes":18276,"imports":[{"path":"node_modules/react/index.js","kind":"import-statement","original":"react"},{"path":"node_modules/@remix-run/router/dist/router.js","kind":"import-statement","original":"@remix-run/router"},{"path":"node_modules/react-router-dom/dist/index.js","kind":"import-statement","original":"react-router-dom"},{"path":"node_modules/@remix-run/react/dist/esm/routeModules.js","kind":"import-statement","original":"./routeModules.js"},{"path":"node_modules/@remix-run/react/dist/esm/data.js","kind":"import-statement","original":"./data.js"},{"path":"node_modules/@remix-run/react/dist/esm/links.js","kind":"import-statement","original":"./links.js"},{"path":"node_modules/@remix-run/react/dist/esm/errorBoundaries.js","kind":"import-statement","original":"./errorBoundaries.js"},{"path":"node_modules/@remix-run/react/dist/esm/fallback.js","kind":"import-statement","original":"./fallback.js"},{"path":"node_modules/@remix-run/react/dist/esm/invariant.js","kind":"import-statement","original":"./invariant.js"}],"format":"esm"},"node_modules/@remix-run/react/dist/esm/fog-of-war.js":{"bytes":7594,"imports":[{"path":"node_modules/@remix-run/router/dist/router.js","kind":"import-statement","original":"@remix-run/router"},{"path":"node_modules/react/index.js","kind":"import-statement","original":"react"},{"path":"node_modules/@remix-run/react/dist/esm/routes.js","kind":"import-statement","original":"./routes.js"}],"format":"esm"},"node_modules/@remix-run/react/dist/esm/components.js":{"bytes":35459,"imports":[{"path":"node_modules/@remix-run/react/dist/esm/_virtual/_rollupPluginBabelHelpers.js","kind":"import-statement","original":"./_virtual/_rollupPluginBabelHelpers.js"},{"path":"node_modules/react/index.js","kind":"import-statement","original":"react"},{"path":"node_modules/react-router-dom/dist/index.js","kind":"import-statement","original":"react-router-dom"},{"path":"node_modules/@remix-run/react/dist/esm/invariant.js","kind":"import-statement","original":"./invariant.js"},{"path":"node_modules/@remix-run/react/dist/esm/links.js","kind":"import-statement","original":"./links.js"},{"path":"node_modules/@remix-run/react/dist/esm/markup.js","kind":"import-statement","original":"./markup.js"},{"path":"node_modules/@remix-run/react/dist/esm/single-fetch.js","kind":"import-statement","original":"./single-fetch.js"},{"path":"node_modules/@remix-run/react/dist/esm/fog-of-war.js","kind":"import-statement","original":"./fog-of-war.js"}],"format":"esm"},"node_modules/@remix-run/react/dist/esm/errors.js":{"bytes":1581,"imports":[{"path":"node_modules/@remix-run/router/dist/router.js","kind":"import-statement","original":"@remix-run/router"}],"format":"esm"},"node_modules/@remix-run/react/dist/esm/browser.js":{"bytes":14034,"imports":[{"path":"hmr-runtime:remix:hmr","kind":"import-statement","original":"remix:hmr"},{"path":"node_modules/@remix-run/router/dist/router.js","kind":"import-statement","original":"@remix-run/router"},{"path":"node_modules/react/index.js","kind":"import-statement","original":"react"},{"path":"node_modules/react-router/dist/index.js","kind":"import-statement","original":"react-router"},{"path":"node_modules/react-router-dom/dist/index.js","kind":"import-statement","original":"react-router-dom"},{"path":"node_modules/@remix-run/react/dist/esm/components.js","kind":"import-statement","original":"./components.js"},{"path":"node_modules/@remix-run/react/dist/esm/errorBoundaries.js","kind":"import-statement","original":"./errorBoundaries.js"},{"path":"node_modules/@remix-run/react/dist/esm/errors.js","kind":"import-statement","original":"./errors.js"},{"path":"node_modules/@remix-run/react/dist/esm/routes.js","kind":"import-statement","original":"./routes.js"},{"path":"node_modules/@remix-run/react/dist/esm/single-fetch.js","kind":"import-statement","original":"./single-fetch.js"},{"path":"node_modules/@remix-run/react/dist/esm/invariant.js","kind":"import-statement","original":"./invariant.js"},{"path":"node_modules/@remix-run/react/dist/esm/fog-of-war.js","kind":"import-statement","original":"./fog-of-war.js"}],"format":"esm"},"node_modules/@remix-run/react/dist/esm/scroll-restoration.js":{"bytes":2665,"imports":[{"path":"node_modules/@remix-run/react/dist/esm/_virtual/_rollupPluginBabelHelpers.js","kind":"import-statement","original":"./_virtual/_rollupPluginBabelHelpers.js"},{"path":"node_modules/react/index.js","kind":"import-statement","original":"react"},{"path":"node_modules/react-router-dom/dist/index.js","kind":"import-statement","original":"react-router-dom"},{"path":"node_modules/@remix-run/react/dist/esm/components.js","kind":"import-statement","original":"./components.js"}],"format":"esm"},"node_modules/react-router-dom/server.js":{"bytes":10633,"imports":[{"path":"node_modules/react/index.js","kind":"require-call","original":"react"},{"path":"node_modules/@remix-run/router/dist/router.js","kind":"require-call","original":"@remix-run/router"},{"path":"node_modules/react-router/dist/index.js","kind":"require-call","original":"react-router"},{"path":"node_modules/react-router-dom/dist/index.js","kind":"require-call","original":"react-router-dom"}],"format":"cjs"},"node_modules/@remix-run/react/dist/esm/server.js":{"bytes":3417,"imports":[{"path":"node_modules/react/index.js","kind":"import-statement","original":"react"},{"path":"node_modules/react-router-dom/server.js","kind":"import-statement","original":"react-router-dom/server"},{"path":"node_modules/@remix-run/react/dist/esm/components.js","kind":"import-statement","original":"./components.js"},{"path":"node_modules/@remix-run/react/dist/esm/errorBoundaries.js","kind":"import-statement","original":"./errorBoundaries.js"},{"path":"node_modules/@remix-run/react/dist/esm/routes.js","kind":"import-statement","original":"./routes.js"},{"path":"node_modules/@remix-run/react/dist/esm/single-fetch.js","kind":"import-statement","original":"./single-fetch.js"}],"format":"esm"},"node_modules/@remix-run/react/dist/esm/index.js":{"bytes":1347,"imports":[{"path":"node_modules/react-router-dom/dist/index.js","kind":"import-statement","original":"react-router-dom"},{"path":"node_modules/@remix-run/server-runtime/dist/esm/index.js","kind":"import-statement","original":"@remix-run/server-runtime"},{"path":"node_modules/@remix-run/react/dist/esm/browser.js","kind":"import-statement","original":"./browser.js"},{"path":"node_modules/@remix-run/react/dist/esm/components.js","kind":"import-statement","original":"./components.js"},{"path":"node_modules/@remix-run/react/dist/esm/scroll-restoration.js","kind":"import-statement","original":"./scroll-restoration.js"},{"path":"node_modules/@remix-run/react/dist/esm/server.js","kind":"import-statement","original":"./server.js"}],"format":"esm"},"node_modules/react-dom/client.js":{"bytes":619,"imports":[{"path":"node_modules/react-dom/index.js","kind":"require-call","original":"react-dom"}],"format":"cjs"},"node_modules/react/cjs/react-jsx-dev-runtime.development.js":{"bytes":41147,"imports":[{"path":"node_modules/react/index.js","kind":"require-call","original":"react"}],"format":"cjs"},"node_modules/react/jsx-dev-runtime.js":{"bytes":222,"imports":[{"path":"node_modules/react/cjs/react-jsx-dev-runtime.development.js","kind":"require-call","original":"./cjs/react-jsx-dev-runtime.development.js"}],"format":"cjs"},"node_modules/@remix-run/dev/dist/config/defaults/entry.client.tsx":{"bytes":271,"imports":[{"path":"node_modules/@remix-run/react/dist/esm/index.js","kind":"import-statement","original":"@remix-run/react"},{"path":"node_modules/react/index.js","kind":"import-statement","original":"react"},{"path":"node_modules/react-dom/client.js","kind":"import-statement","original":"react-dom/client"},{"path":"node_modules/react/jsx-dev-runtime.js","kind":"import-statement","original":"react/jsx-dev-runtime"}],"format":"esm"},"app/root.jsx":{"bytes":1439,"imports":[{"path":"hmr-runtime:remix:hmr","kind":"import-statement","original":"remix:hmr"},{"path":"node_modules/@remix-run/react/dist/esm/index.js","kind":"import-statement","original":"@remix-run/react"},{"path":"node_modules/react/jsx-dev-runtime.js","kind":"import-statement","original":"react/jsx-dev-runtime"}],"format":"esm"},"browser-route-module:root.jsx?browser":{"bytes":44,"imports":[{"path":"app/root.jsx","kind":"import-statement","original":"./root.jsx"}],"format":"esm"},"app/routes/index.jsx":{"bytes":1511,"imports":[{"path":"hmr-runtime:remix:hmr","kind":"import-statement","original":"remix:hmr"},{"path":"react","kind":"import-statement","external":true},{"path":"node_modules/react/jsx-dev-runtime.js","kind":"import-statement","original":"react/jsx-dev-runtime"}],"format":"esm"},"browser-route-module:routes/index.jsx?browser":{"bytes":45,"imports":[{"path":"app/routes/index.jsx","kind":"import-statement","original":"./routes/index.jsx"}],"format":"esm"},"app/routes/panel.jsx":{"bytes":2401,"imports":[{"path":"hmr-runtime:remix:hmr","kind":"import-statement","original":"remix:hmr"},{"path":"react","kind":"import-statement","external":true},{"path":"node_modules/react/jsx-dev-runtime.js","kind":"import-statement","original":"react/jsx-dev-runtime"}],"format":"esm"},"browser-route-module:routes/panel.jsx?browser":{"bytes":45,"imports":[{"path":"app/routes/panel.jsx","kind":"import-statement","original":"./routes/panel.jsx"}],"format":"esm"},"node_modules/react/cjs/react-jsx-runtime.development.js":{"bytes":41746,"imports":[{"path":"node_modules/react/index.js","kind":"require-call","original":"react"}],"format":"cjs"},"node_modules/react/jsx-runtime.js":{"bytes":214,"imports":[{"path":"node_modules/react/cjs/react-jsx-runtime.development.js","kind":"require-call","original":"./cjs/react-jsx-runtime.development.js"}],"format":"cjs"},"node_modules/@remix-run/dev/dist/config/defaults/entry.dev.ts":{"bytes":289,"imports":[{"path":"node_modules/react/index.js","kind":"dynamic-import","original":"react"},{"path":"node_modules/react/jsx-dev-runtime.js","kind":"dynamic-import","original":"react/jsx-dev-runtime"},{"path":"node_modules/react/jsx-runtime.js","kind":"dynamic-import","original":"react/jsx-runtime"},{"path":"node_modules/react-dom/index.js","kind":"dynamic-import","original":"react-dom"},{"path":"node_modules/react-dom/client.js","kind":"dynamic-import","original":"react-dom/client"},{"path":"node_modules/react-refresh/runtime.js","kind":"dynamic-import","original":"react-refresh/runtime"},{"path":"node_modules/@remix-run/react/dist/esm/index.js","kind":"dynamic-import","original":"@remix-run/react"},{"path":"hmr-runtime:remix:hmr","kind":"dynamic-import","original":"remix:hmr"}],"format":"esm"}},"outputs":{"public/build/_shared/remix_hmr-2XLZ672O.js.map":{"imports":[],"exports":[],"inputs":{},"bytes":93},"public/build/_shared/remix_hmr-2XLZ672O.js":{"imports":[{"path":"public/build/_shared/chunk-5HSLDJTJ.js","kind":"import-statement"},{"path":"public/build/_shared/chunk-UWV35TSL.js","kind":"import-statement"},{"path":"public/build/_shared/chunk-PNG5AS42.js","kind":"import-statement"}],"exports":["createHotContext"],"entryPoint":"hmr-runtime:remix:hmr","inputs":{},"bytes":250},"public/build/_shared/esm-HCCAVYH5.js.map":{"imports":[],"exports":[],"inputs":{},"bytes":93},"public/build/_shared/esm-HCCAVYH5.js":{"imports":[{"path":"public/build/_shared/chunk-2MYUCU7P.js","kind":"import-statement"},{"path":"public/build/_shared/chunk-5HSLDJTJ.js","kind":"import-statement"},{"path":"public/build/_shared/chunk-GIAAE3CH.js","kind":"import-statement"},{"path":"public/build/_shared/chunk-BOXFZXVX.js","kind":"import-statement"},{"path":"public/build/_shared/chunk-UWV35TSL.js","kind":"import-statement"},{"path":"public/build/_shared/chunk-PNG5AS42.js","kind":"import-statement"}],"exports":["Await","Form","Link","Links","LiveReload","Meta","NavLink","Navigate","NavigationType","Outlet","PrefetchPageLinks","RemixBrowser","RemixServer","Route","Routes","Scripts","ScrollRestoration","UNSAFE_RemixContext","createPath","createRoutesFromChildren","createRoutesFromElements","createSearchParams","data","defer","generatePath","isRouteErrorResponse","json","matchPath","matchRoutes","parsePath","redirect","redirectDocument","renderMatches","replace","resolvePath","unstable_usePrompt","useActionData","useAsyncError","useAsyncValue","useBeforeUnload","useBlocker","useFetcher","useFetchers","useFormAction","useHref","useInRouterContext","useLinkClickHandler","useLoaderData","useLocation","useMatch","useMatches","useNavigate","useNavigation","useNavigationType","useOutlet","useOutletContext","useParams","useResolvedPath","useRevalidator","useRouteError","useRouteLoaderData","useRoutes","useSearchParams","useSubmit","useViewTransitionState"],"entryPoint":"node_modules/@remix-run/react/dist/esm/index.js","inputs":{},"bytes":2384},"public/build/_shared/client-DFZR44C7.js.map":{"imports":[],"exports":[],"inputs":{},"bytes":93},"public/build/_shared/client-DFZR44C7.js":{"imports":[{"path":"public/build/_shared/chunk-ZWGWGGVF.js","kind":"import-statement"},{"path":"public/build/_shared/chunk-GIAAE3CH.js","kind":"import-statement"},{"path":"public/build/_shared/chunk-BOXFZXVX.js","kind":"import-statement"},{"path":"public/build/_shared/chunk-PNG5AS42.js","kind":"import-statement"}],"exports":["default"],"entryPoint":"node_modules/react-dom/client.js","inputs":{},"bytes":290},"public/build/_shared/jsx-dev-runtime-RDH4Y5YT.js.map":{"imports":[],"exports":[],"inputs":{},"bytes":93},"public/build/_shared/jsx-dev-runtime-RDH4Y5YT.js":{"imports":[{"path":"public/build/_shared/chunk-XU7DNSPJ.js","kind":"import-statement"},{"path":"public/build/_shared/chunk-BOXFZXVX.js","kind":"import-statement"},{"path":"public/build/_shared/chunk-PNG5AS42.js","kind":"import-statement"}],"exports":["default"],"entryPoint":"node_modules/react/jsx-dev-runtime.js","inputs":{},"bytes":274},"public/build/_shared/jsx-runtime-7NXSP56X.js.map":{"imports":[],"exports":[],"inputs":{},"bytes":60514},"public/build/_shared/jsx-runtime-7NXSP56X.js":{"imports":[{"path":"public/build/_shared/chunk-BOXFZXVX.js","kind":"import-statement"},{"path":"public/build/_shared/chunk-PNG5AS42.js","kind":"import-statement"}],"exports":["default"],"entryPoint":"node_modules/react/jsx-runtime.js","inputs":{"node_modules/react/cjs/react-jsx-runtime.development.js":{"bytesInOutput":35395},"node_modules/react/jsx-runtime.js":{"bytesInOutput":233}},"bytes":36306},"public/build/entry.client-MK4DPPFG.js.map":{"imports":[],"exports":[],"inputs":{},"bytes":676},"public/build/entry.client-MK4DPPFG.js":{"imports":[{"path":"public/build/_shared/chunk-ZWGWGGVF.js","kind":"import-statement"},{"path":"public/build/_shared/chunk-2MYUCU7P.js","kind":"import-statement"},{"path":"public/build/_shared/chunk-5HSLDJTJ.js","kind":"import-statement"},{"path":"public/build/_shared/chunk-XU7DNSPJ.js","kind":"import-statement"},{"path":"public/build/_shared/chunk-GIAAE3CH.js","kind":"import-statement"},{"path":"public/build/_shared/chunk-BOXFZXVX.js","kind":"import-statement"},{"path":"public/build/_shared/chunk-UWV35TSL.js","kind":"import-statement"},{"path":"public/build/_shared/chunk-PNG5AS42.js","kind":"import-statement"}],"exports":[],"entryPoint":"node_modules/@remix-run/dev/dist/config/defaults/entry.client.tsx","inputs":{"node_modules/@remix-run/dev/dist/config/defaults/entry.client.tsx":{"bytesInOutput":739}},"bytes":1339},"public/build/_shared/chunk-ZWGWGGVF.js.map":{"imports":[],"exports":[],"inputs":{},"bytes":1228},"public/build/_shared/chunk-ZWGWGGVF.js":{"imports":[{"path":"public/build/_shared/chunk-GIAAE3CH.js","kind":"import-statement"},{"path":"public/build/_shared/chunk-PNG5AS42.js","kind":"import-statement"}],"exports":["require_client"],"inputs":{"node_modules/react-dom/client.js":{"bytesInOutput":760}},"bytes":1022},"public/build/root-M6QQDY6U.js.map":{"imports":[],"exports":[],"inputs":{},"bytes":2695},"public/build/root-M6QQDY6U.js":{"imports":[{"path":"public/build/_shared/chunk-2MYUCU7P.js","kind":"import-statement"},{"path":"public/build/_shared/chunk-5HSLDJTJ.js","kind":"import-statement"},{"path":"public/build/_shared/chunk-XU7DNSPJ.js","kind":"import-statement"},{"path":"public/build/_shared/chunk-GIAAE3CH.js","kind":"import-statement"},{"path":"public/build/_shared/chunk-BOXFZXVX.js","kind":"import-statement"},{"path":"public/build/_shared/chunk-UWV35TSL.js","kind":"import-statement"},{"path":"public/build/_shared/chunk-PNG5AS42.js","kind":"import-statement"}],"exports":["default","links"],"entryPoint":"browser-route-module:root.jsx?browser","inputs":{"app/root.jsx":{"bytesInOutput":3049},"browser-route-module:root.jsx?browser":{"bytesInOutput":0}},"bytes":3617},"public/build/_shared/chunk-2MYUCU7P.js.map":{"imports":[],"exports":[],"inputs":{},"bytes":845019},"public/build/_shared/chunk-2MYUCU7P.js":{"imports":[{"path":"public/build/_shared/chunk-5HSLDJTJ.js","kind":"import-statement"},{"path":"public/build/_shared/chunk-GIAAE3CH.js","kind":"import-statement"},{"path":"public/build/_shared/chunk-BOXFZXVX.js","kind":"import-statement"},{"path":"public/build/_shared/chunk-PNG5AS42.js","kind":"import-statement"}],"exports":["Action","Await","Form","Link","Links","LiveReload","Meta","NavLink","Navigate","Outlet","PrefetchPageLinks","RemixBrowser","RemixContext","RemixServer","Route","Routes","Scripts","ScrollRestoration","createPath","createRoutesFromChildren","createSearchParams","data","defer","generatePath","isRouteErrorResponse","json","matchPath","matchRoutes","parsePath","redirect","redirectDocument","renderMatches","replace","resolvePath","useActionData","useAsyncError","useAsyncValue","useBeforeUnload","useBlocker","useFetcher","useFetchers","useFormAction","useHref","useInRouterContext","useLinkClickHandler","useLoaderData","useLocation","useMatch","useMatches","useNavigate","useNavigation","useNavigationType","useOutlet","useOutletContext","useParams","usePrompt","useResolvedPath","useRevalidator","useRouteError","useRouteLoaderData","useRoutes","useSearchParams","useSubmit","useViewTransitionState"],"inputs":{"node_modules/@remix-run/router/dist/router.js":{"bytesInOutput":144525},"node_modules/react-router/dist/index.js":{"bytesInOutput":45092},"node_modules/react-router-dom/dist/index.js":{"bytesInOutput":44303},"node_modules/react-router-dom/server.js":{"bytesInOutput":10663},"node_modules/@remix-run/react/dist/esm/index.js":{"bytesInOutput":14},"node_modules/@remix-run/server-runtime/dist/esm/responses.js":{"bytesInOutput":381},"node_modules/@remix-run/server-runtime/dist/esm/index.js":{"bytesInOutput":0},"node_modules/@remix-run/server-runtime/dist/esm/single-fetch.js":{"bytesInOutput":138},"node_modules/turbo-stream/dist/turbo-stream.mjs":{"bytesInOutput":9924},"node_modules/@remix-run/react/dist/esm/browser.js":{"bytesInOutput":9087},"node_modules/@remix-run/react/dist/esm/_virtual/_rollupPluginBabelHelpers.js":{"bytesInOutput":404},"node_modules/@remix-run/react/dist/esm/components.js":{"bytesInOutput":28775},"node_modules/@remix-run/react/dist/esm/invariant.js":{"bytesInOutput":149},"node_modules/@remix-run/react/dist/esm/links.js":{"bytesInOutput":7770},"node_modules/@remix-run/react/dist/esm/routeModules.js":{"bytesInOutput":658},"node_modules/@remix-run/react/dist/esm/markup.js":{"bytesInOutput":328},"node_modules/@remix-run/react/dist/esm/single-fetch.js":{"bytesInOutput":10212},"node_modules/@remix-run/react/dist/esm/data.js":{"bytesInOutput":7360},"node_modules/@remix-run/react/dist/esm/fog-of-war.js":{"bytesInOutput":5902},"node_modules/@remix-run/react/dist/esm/routes.js":{"bytesInOutput":15018},"node_modules/@remix-run/react/dist/esm/errorBoundaries.js":{"bytesInOutput":3394},"node_modules/@remix-run/react/dist/esm/fallback.js":{"bytesInOutput":680},"node_modules/@remix-run/react/dist/esm/errors.js":{"bytesInOutput":962},"node_modules/@remix-run/react/dist/esm/scroll-restoration.js":{"bytesInOutput":1553},"node_modules/@remix-run/react/dist/esm/server.js":{"bytesInOutput":2140}},"bytes":359464},"public/build/routes/index-O6Q2NIUT.js.map":{"imports":[],"exports":[],"inputs":{},"bytes":2506},"public/build/routes/index-O6Q2NIUT.js":{"imports":[{"path":"public/build/_shared/chunk-5HSLDJTJ.js","kind":"import-statement"},{"path":"public/build/_shared/chunk-XU7DNSPJ.js","kind":"import-statement"},{"path":"public/build/_shared/chunk-BOXFZXVX.js","kind":"import-statement"},{"path":"public/build/_shared/chunk-UWV35TSL.js","kind":"import-statement"},{"path":"public/build/_shared/chunk-PNG5AS42.js","kind":"import-statement"}],"exports":["default"],"entryPoint":"browser-route-module:routes/index.jsx?browser","inputs":{"app/routes/index.jsx":{"bytesInOutput":2353},"browser-route-module:routes/index.jsx?browser":{"bytesInOutput":0}},"bytes":2763},"public/build/routes/panel-FC6O53XJ.js.map":{"imports":[],"exports":[],"inputs":{},"bytes":4188},"public/build/routes/panel-FC6O53XJ.js":{"imports":[{"path":"public/build/_shared/chunk-5HSLDJTJ.js","kind":"import-statement"},{"path":"public/build/_shared/chunk-XU7DNSPJ.js","kind":"import-statement"},{"path":"public/build/_shared/chunk-BOXFZXVX.js","kind":"import-statement"},{"path":"public/build/_shared/chunk-UWV35TSL.js","kind":"import-statement"},{"path":"public/build/_shared/chunk-PNG5AS42.js","kind":"import-statement"}],"exports":["default"],"entryPoint":"browser-route-module:routes/panel.jsx?browser","inputs":{"app/routes/panel.jsx":{"bytesInOutput":5215},"browser-route-module:routes/panel.jsx?browser":{"bytesInOutput":0}},"bytes":5625},"public/build/_shared/chunk-5HSLDJTJ.js.map":{"imports":[],"exports":[],"inputs":{},"bytes":3327},"public/build/_shared/chunk-5HSLDJTJ.js":{"imports":[{"path":"public/build/_shared/chunk-UWV35TSL.js","kind":"import-statement"},{"path":"public/build/_shared/chunk-PNG5AS42.js","kind":"import-statement"}],"exports":["createHotContext"],"inputs":{"hmr-runtime:remix:hmr":{"bytesInOutput":1648}},"bytes":1896},"public/build/_shared/chunk-XU7DNSPJ.js.map":{"imports":[],"exports":[],"inputs":{},"bytes":59687},"public/build/_shared/chunk-XU7DNSPJ.js":{"imports":[{"path":"public/build/_shared/chunk-BOXFZXVX.js","kind":"import-statement"},{"path":"public/build/_shared/chunk-PNG5AS42.js","kind":"import-statement"}],"exports":["require_jsx_dev_runtime"],"inputs":{"node_modules/react/cjs/react-jsx-dev-runtime.development.js":{"bytesInOutput":35020},"node_modules/react/jsx-dev-runtime.js":{"bytesInOutput":245}},"bytes":35954},"public/build/__remix_entry_dev-ALFDFL3J.js.map":{"imports":[],"exports":[],"inputs":{},"bytes":652},"public/build/__remix_entry_dev-ALFDFL3J.js":{"imports":[{"path":"public/build/_shared/chunk-PNG5AS42.js","kind":"import-statement"},{"path":"public/build/_shared/react-3OYUNTOK.js","kind":"dynamic-import"},{"path":"public/build/_shared/jsx-dev-runtime-RDH4Y5YT.js","kind":"dynamic-import"},{"path":"public/build/_shared/jsx-runtime-7NXSP56X.js","kind":"dynamic-import"},{"path":"public/build/_shared/react-dom-BEFB7ICU.js","kind":"dynamic-import"},{"path":"public/build/_shared/client-DFZR44C7.js","kind":"dynamic-import"},{"path":"public/build/_shared/runtime-GC7QIU56.js","kind":"dynamic-import"},{"path":"public/build/_shared/esm-HCCAVYH5.js","kind":"dynamic-import"},{"path":"public/build/_shared/remix_hmr-2XLZ672O.js","kind":"dynamic-import"}],"exports":["default"],"entryPoint":"node_modules/@remix-run/dev/dist/config/defaults/entry.dev.ts","inputs":{"node_modules/@remix-run/dev/dist/config/defaults/entry.dev.ts":{"bytesInOutput":428}},"bytes":642},"public/build/_shared/react-3OYUNTOK.js.map":{"imports":[],"exports":[],"inputs":{},"bytes":93},"public/build/_shared/react-3OYUNTOK.js":{"imports":[{"path":"public/build/_shared/chunk-BOXFZXVX.js","kind":"import-statement"},{"path":"public/build/_shared/chunk-PNG5AS42.js","kind":"import-statement"}],"exports":["default"],"entryPoint":"node_modules/react/index.js","inputs":{},"bytes":201},"public/build/_shared/react-dom-BEFB7ICU.js.map":{"imports":[],"exports":[],"inputs":{},"bytes":93},"public/build/_shared/react-dom-BEFB7ICU.js":{"imports":[{"path":"public/build/_shared/chunk-GIAAE3CH.js","kind":"import-statement"},{"path":"public/build/_shared/chunk-BOXFZXVX.js","kind":"import-statement"},{"path":"public/build/_shared/chunk-PNG5AS42.js","kind":"import-statement"}],"exports":["default"],"entryPoint":"node_modules/react-dom/index.js","inputs":{},"bytes":256},"public/build/_shared/chunk-GIAAE3CH.js.map":{"imports":[],"exports":[],"inputs":{},"bytes":1488526},"public/build/_shared/chunk-GIAAE3CH.js":{"imports":[{"path":"public/build/_shared/chunk-BOXFZXVX.js","kind":"import-statement"},{"path":"public/build/_shared/chunk-PNG5AS42.js","kind":"import-statement"}],"exports":["require_react_dom"],"inputs":{"node_modules/scheduler/cjs/scheduler.development.js":{"bytesInOutput":16890},"node_modules/scheduler/index.js":{"bytesInOutput":239},"node_modules/react-dom/cjs/react-dom.development.js":{"bytesInOutput":906463},"node_modules/react-dom/index.js":{"bytesInOutput":239}},"bytes":925313},"public/build/_shared/chunk-BOXFZXVX.js.map":{"imports":[],"exports":[],"inputs":{},"bytes":125599},"public/build/_shared/chunk-BOXFZXVX.js":{"imports":[{"path":"public/build/_shared/chunk-PNG5AS42.js","kind":"import-statement"}],"exports":["require_react"],"inputs":{"node_modules/react/cjs/react.development.js":{"bytesInOutput":77023},"node_modules/react/index.js":{"bytesInOutput":209}},"bytes":77785},"public/build/_shared/runtime-GC7QIU56.js.map":{"imports":[],"exports":[],"inputs":{},"bytes":93},"public/build/_shared/runtime-GC7QIU56.js":{"imports":[{"path":"public/build/_shared/chunk-UWV35TSL.js","kind":"import-statement"},{"path":"public/build/_shared/chunk-PNG5AS42.js","kind":"import-statement"}],"exports":["default"],"entryPoint":"node_modules/react-refresh/runtime.js","inputs":{},"bytes":207},"public/build/_shared/chunk-UWV35TSL.js.map":{"imports":[],"exports":[],"inputs":{},"bytes":30368},"public/build/_shared/chunk-UWV35TSL.js":{"imports":[{"path":"public/build/_shared/chunk-PNG5AS42.js","kind":"import-statement"}],"exports":["require_runtime"],"inputs":{"node_modules/react-refresh/cjs/react-refresh-runtime.development.js":{"bytesInOutput":17196},"node_modules/react-refresh/runtime.js":{"bytesInOutput":237}},"bytes":18062},"public/build/_shared/chunk-PNG5AS42.js.map":{"imports":[],"exports":[],"inputs":{},"bytes":93},"public/build/_shared/chunk-PNG5AS42.js":{"imports":[],"exports":["__commonJS","__esm","__export","__toCommonJS","__toESM"],"inputs":{},"bytes":1791}}}